nonebot_plugin_blocker-0.4.8.dist-info/METADATA
nonebot_plugin_blocker-0.4.8.dist-info/WHEEL
nonebot_plugin_blocker-0.4.8.dist-info/licenses/LICENSE
nonebot_plugin_blocker/__init__.py
nonebot_plugin_blocker/__main__.py
nonebot_plugin_blocker/config.py
nonebot_plugin_blocker/web/__init__.py
nonebot_plugin_blocker/web/webpage/main.html
nonebot_plugin_blocker/web/webpage/main.js
nonebot_plugin_blocker/web/webpage/style.css
nonebot_plugin_blocker-0.4.8.dist-info/RECORD
