Metadata-Version: 2.1
Name: nonebot-plugin-blocker
Version: 0.4.8
Summary: Message Blocker
Keywords: nonebot nonebot2 qqbot bot
Home-page: https://github.com/MerCuJerry/nonebot-plugin-blocker
Author-Email: MerCuJerry <mercujerry@gmail.com>
License: MIT License
Project-URL: Homepage, https://github.com/MerCuJerry/nonebot-plugin-blocker
Requires-Python: <4.0,>=3.8
Requires-Dist: nonebot2[fastapi]>=2.2.1
Requires-Dist: nonebot-adapter-onebot>=2.4.1
Requires-Dist: pydantic!=2.5.0,!=2.5.1,<3.0.0,>=2.0
